{
  "direct_dep_identities": [
    "ios-maps-sdk"
  ],
  "modules": [
    {
      "name": "GoogleMaps",
      "c99name": "GoogleMaps",
      "src_type": "binary",
      "label": "@swiftpkg_ios_maps_sdk//:GoogleMaps.rspm",
      "package_identity": "ios-maps-sdk",
      "product_memberships": [
        "GoogleMaps"
      ]
    },
    {
      "name": "GoogleMapsBase",
      "c99name": "GoogleMapsBase",
      "src_type": "binary",
      "label": "@swiftpkg_ios_maps_sdk//:GoogleMapsBase.rspm",
      "package_identity": "ios-maps-sdk",
      "product_memberships": [
        "GoogleMaps"
      ]
    },
    {
      "name": "GoogleMapsBaseTarget",
      "c99name": "GoogleMapsBaseTarget",
      "src_type": "objc",
      "label": "@swiftpkg_ios_maps_sdk//:GoogleMapsBaseTarget.rspm",
      "package_identity": "ios-maps-sdk",
      "product_memberships": [
        "GoogleMaps"
      ]
    },
    {
      "name": "GoogleMapsCore",
      "c99name": "GoogleMapsCore",
      "src_type": "binary",
      "label": "@swiftpkg_ios_maps_sdk//:GoogleMapsCore.rspm",
      "package_identity": "ios-maps-sdk",
      "product_memberships": [
        "GoogleMaps"
      ]
    },
    {
      "name": "GoogleMapsCoreTarget",
      "c99name": "GoogleMapsCoreTarget",
      "src_type": "objc",
      "label": "@swiftpkg_ios_maps_sdk//:GoogleMapsCoreTarget.rspm",
      "package_identity": "ios-maps-sdk",
      "product_memberships": [
        "GoogleMaps"
      ]
    },
    {
      "name": "GoogleMapsTarget",
      "c99name": "GoogleMapsTarget",
      "src_type": "objc",
      "label": "@swiftpkg_ios_maps_sdk//:GoogleMapsTarget.rspm",
      "package_identity": "ios-maps-sdk",
      "product_memberships": [
        "GoogleMaps"
      ]
    }
  ],
  "products": [
    {
      "identity": "ios-maps-sdk",
      "name": "GoogleMaps",
      "type": "library",
      "label": "@swiftpkg_ios_maps_sdk//:GoogleMaps"
    }
  ],
  "packages": [
    {
      "name": "swiftpkg_ios_maps_sdk",
      "identity": "ios-maps-sdk",
      "remote": {
        "commit": "0cd72dd45109b0225dd920ff17e0362a96489ec0",
        "remote": "https://github.com/googlemaps/ios-maps-sdk",
        "version": "9.0.0",
        "patch": {
          "files": [
            "@@//third-party/google-maps-ios-sdk:0001-Remove-import-GoogleMaps.patch"
          ],
          "args": [
            "-p1"
          ]
        }
      }
    }
  ]
}